odoo/addons/product_profile/README.rst
odoo/addons/product_profile/__init__.py
odoo/addons/product_profile/__manifest__.py
odoo/addons/product_profile/i18n/ca.po
odoo/addons/product_profile/i18n/de.po
odoo/addons/product_profile/i18n/es.po
odoo/addons/product_profile/i18n/fr.po
odoo/addons/product_profile/i18n/hr.po
odoo/addons/product_profile/i18n/it.po
odoo/addons/product_profile/i18n/nl_NL.po
odoo/addons/product_profile/i18n/product_profile.pot
odoo/addons/product_profile/i18n/sl.po
odoo/addons/product_profile/models/__init__.py
odoo/addons/product_profile/models/config.py
odoo/addons/product_profile/models/product.py
odoo/addons/product_profile/models/product_profile.py
odoo/addons/product_profile/readme/CONFIGURE.rst
odoo/addons/product_profile/readme/CONTRIBUTORS.rst
odoo/addons/product_profile/readme/DESCRIPTION.rst
odoo/addons/product_profile/readme/ROADMAP.rst
odoo/addons/product_profile/readme/USAGE.rst
odoo/addons/product_profile/security/group.xml
odoo/addons/product_profile/security/ir.model.access.csv
odoo/addons/product_profile/static/description/icon.png
odoo/addons/product_profile/static/description/index.html
odoo/addons/product_profile/static/img/field.png
odoo/addons/product_profile/static/img/list.png
odoo/addons/product_profile/views/config_view.xml
odoo/addons/product_profile/views/product_view.xml
odoo14_addon_product_profile-14.0.1.0.1.dist-info/METADATA
odoo14_addon_product_profile-14.0.1.0.1.dist-info/WHEEL
odoo14_addon_product_profile-14.0.1.0.1.dist-info/top_level.txt
odoo14_addon_product_profile-14.0.1.0.1.dist-info/RECORD
